{
  "team": "Samsung Lions",
  "slug": "samsung",
  "updatedAt": "2026-04-03T01:22:33+09:00",
  "last10": [
    {
      "date": "2026-04-02",
      "result": "W",
      "opponent": "두산",
      "homeAway": "home",
      "score": "5-2",
      "stadium": "대구",
      "winningPitcher": "최지광",
      "losingPitcher": "타무라",
      "savePitcher": "",
      "gameId": "20260402OBSS0",
      "standoutHitter": {
        "name": "김성윤",
        "stat": "20.8%(4타수 1득점 2안타 0타점)",
        "rank": 1
      },
      "standoutPitcher": {
        "name": "이승현",
        "stat": "2회초 1루수 라인드라이브 아웃승리확률48.2% → 55.4%",
        "rank": 3
      }
    },
    {
      "date": "2026-04-01",
      "result": "W",
      "opponent": "두산",
      "homeAway": "home",
      "score": "13-3",
      "stadium": "대구",
      "winningPitcher": "양창섭",
      "losingPitcher": "최승용",
      "savePitcher": "",
      "gameId": "20260401OBSS0",
      "standoutHitter": {
        "name": "김성윤",
        "stat": "14.7%(5타수 3득점 4안타 4타점)",
        "rank": 1
      },
      "standoutPitcher": {
        "name": "양창섭",
        "stat": "5회초 중견수 플라이 아웃승리확률90.8% → 93.8%",
        "rank": 1
      }
    },
    {
      "date": "2026-03-31",
      "result": "D",
      "opponent": "두산",
      "homeAway": "home",
      "score": "5-5",
      "stadium": "대구",
      "winningPitcher": "",
      "losingPitcher": "",
      "savePitcher": "",
      "gameId": "20260331OBSS0",
      "standoutHitter": {
        "name": "디아즈",
        "stat": "24.8%(5타수 1득점 1안타 3타점)",
        "rank": 1
      },
      "standoutPitcher": {
        "name": "최지광",
        "stat": "10회초 중견수 플라이 아웃승리확률50.6% → 58.6%",
        "rank": 4
      }
    },
    {
      "date": "2026-03-29",
      "result": "L",
      "opponent": "롯데",
      "homeAway": "home",
      "score": "2-6",
      "stadium": "대구",
      "winningPitcher": "비슬리",
      "losingPitcher": "최원태",
      "savePitcher": "",
      "gameId": "20260329LTSS0",
      "standoutHitter": {
        "name": "류지혁",
        "stat": "12.7%(4타수 1득점 2안타 0타점)",
        "rank": 2
      },
      "standoutPitcher": {
        "name": "최원태",
        "stat": "6회초 유격수 병살타 아웃 (유격수->2루수->1루수 송구아웃)승리확률32.3% → 40.6%",
        "rank": 3
      }
    },
    {
      "date": "2026-03-28",
      "result": "L",
      "opponent": "롯데",
      "homeAway": "home",
      "score": "3-6",
      "stadium": "대구",
      "winningPitcher": "로드리게스",
      "losingPitcher": "후라도",
      "savePitcher": "박정민",
      "gameId": "20260328LTSS0",
      "standoutHitter": {
        "name": "전병우",
        "stat": "5.9%(0타수 0득점 0안타 0타점)",
        "rank": 3
      },
      "standoutPitcher": {
        "name": "육선엽",
        "stat": "2",
        "rank": 2
      }
    },
    {
      "date": "2026-03-24",
      "result": "L",
      "opponent": "KIA",
      "homeAway": "home",
      "score": "1-2",
      "stadium": "대구",
      "winningPitcher": "올러",
      "losingPitcher": "오러클린",
      "savePitcher": "정해영",
      "gameId": "20260324HTSS0",
      "standoutHitter": {
        "name": "구자욱",
        "stat": "11.9%(3타수 0득점 1안타 1타점)",
        "rank": 1
      },
      "standoutPitcher": {
        "name": "오러클린",
        "stat": "4",
        "rank": 2
      }
    },
    {
      "date": "2026-03-23",
      "result": "W",
      "opponent": "KIA",
      "homeAway": "home",
      "score": "7-1",
      "stadium": "대구",
      "winningPitcher": "양창섭",
      "losingPitcher": "양현종",
      "savePitcher": "",
      "gameId": "20260323HTSS0",
      "standoutHitter": {
        "name": "김영웅",
        "stat": "23.2%(2타수 2득점 2안타 3타점)",
        "rank": 1
      },
      "standoutPitcher": {
        "name": "양창섭",
        "stat": "3회초 2루수 병살타 아웃 (2루수->유격수->1루수 송구아웃)승리확률56.5% → 65.9%",
        "rank": 1
      }
    },
    {
      "date": "2026-03-22",
      "result": "L",
      "opponent": "LG",
      "homeAway": "home",
      "score": "13-14",
      "stadium": "대구",
      "winningPitcher": "임찬규",
      "losingPitcher": "최원태",
      "savePitcher": "",
      "gameId": "20260322LGSS0",
      "standoutHitter": {
        "name": "구자욱",
        "stat": "21.9%(3타수 0득점 2안타 3타점)",
        "rank": 1
      },
      "standoutPitcher": {
        "name": "최원태",
        "stat": "4",
        "rank": 1
      }
    },
    {
      "date": "2026-03-21",
      "result": "W",
      "opponent": "LG",
      "homeAway": "home",
      "score": "4-3",
      "stadium": "대구",
      "winningPitcher": "후라도",
      "losingPitcher": "이우찬",
      "savePitcher": "김재윤",
      "gameId": "20260321LGSS0",
      "standoutHitter": {
        "name": "이재현",
        "stat": "17.4%(2타수 1득점 1안타 2타점)",
        "rank": 1
      },
      "standoutPitcher": {
        "name": "김재윤",
        "stat": "9회초 3루수 파울플라이 아웃승리확률81.5% → 89.7%",
        "rank": 1
      }
    },
    {
      "date": "2026-03-20",
      "result": "L",
      "opponent": "NC",
      "homeAway": "away",
      "score": "4-6",
      "stadium": "창원",
      "winningPitcher": "배재환",
      "losingPitcher": "김태훈",
      "savePitcher": "류진욱",
      "gameId": "20260320SSNC0",
      "standoutHitter": {
        "name": "김영웅",
        "stat": "11%(4타수 2득점 2안타 2타점)",
        "rank": 2
      },
      "standoutPitcher": {
        "name": "임기영",
        "stat": "4회말 삼진 아웃승리확률55.2% → 62.4%",
        "rank": 1
      }
    }
  ]
}